LICENSE
README.md
setup.py
image_optimizer_cli/__init__.py
image_optimizer_cli/optimize.py
image_optimizer_cli.egg-info/PKG-INFO
image_optimizer_cli.egg-info/SOURCES.txt
image_optimizer_cli.egg-info/dependency_links.txt
image_optimizer_cli.egg-info/entry_points.txt
image_optimizer_cli.egg-info/requires.txt
image_optimizer_cli.egg-info/top_level.txt