Metadata-Version: 2.1
Name: image-optimizer-cli
Version: 2022.1.30
Summary: A PIL based image optimizer
Home-page: https://github.com/egeakman/image-optimizer-cli
Author: Ege Akman
Author-email: egeakmanegeakman@hotmail.com
License: AGPLv3
Download-URL: https://github.com/egeakman/image-optimizer-cli/archive/2022.1.30.tar.gz
Project-URL: Homepage, https://github.com/egeakman/image-optimizer-cli
Project-URL: Issues, https://github.com/egeakman/image-optimizer-cli/issues
Keywords: image,optimize,pillow,PIL,compression,compressor
Platform: UNKNOWN
Classifier: Topic :: Utilities
Classifier: Programming Language :: Python :: 3 :: Only
Classifier: Development Status :: 5 - Production/Stable
Classifier: Environment :: Console
Classifier: License :: OSI Approved :: GNU Affero General Public License v3 or later (AGPLv3+)
Classifier: Operating System :: Microsoft :: Windows
Requires-Python: >=3.6
License-File: LICENSE
